Workbook

Sheet Setup & Targets
A1: Grocery Budget Tracker — Setup
A3: Enter your household info (yellow cells):
A4: Adults | B4: 2
A5: Kids | B5: 0
A6: Monthly take-home income | B6: 5000
A8: Spending style (1=Thrifty, 2=Low-cost, 3=Moderate, 4=Liberal): | B8: 2
A10: Your monthly grocery budget: | B10: =B4*CHOOSE(B8,310,360,450,560)+B5*CHOOSE(B8,230,270,330,400)
A11: Weekly budget: | B11: =B10/4.33
A12: % of income: | B12: =IF(B6>0,B10/B6,0)
A14: Category targets (auto-split of your budget):
A15: Category | B15: Share | C15: Monthly target | D15: Weekly target
A16: Produce | B16: 0.25 | C16: =$B$10*B16 | D16: =C16/4.33
A17: Meat & protein | B17: 0.25 | C17: =$B$10*B17 | D17: =C17/4.33
A18: Dairy & eggs | B18: 0.15 | C18: =$B$10*B18 | D18: =C18/4.33
A19: Pantry & grains | B19: 0.2 | C19: =$B$10*B19 | D19: =C19/4.33
A20: Household & misc | B20: 0.15 | C20: =$B$10*B20 | D20: =C20/4.33
A23: Source: USDA Food Plans average costs, 2026. Category splits are suggested starting points — edit column B to taste.

Sheet Monthly Tracker
A1: Monthly Grocery Tracker
A2: Enter what you actually spend each month. Targets pull from Setup & Targets.
A4: Category | B4: Jan | C4: Feb | D4: Mar | E4: Apr | F4: May | G4: Jun | H4: Jul | I4: Aug | J4: Sep | K4: Oct | L4: Nov | M4: Dec | N4: Total | O4: Target | P4: Over/Under
A5: Produce | N5: =SUM(B5:M5) | O5: ='Setup & Targets'!C16*12 | P5: =N5-O5
A6: Meat & protein | N6: =SUM(B6:M6) | O6: ='Setup & Targets'!C17*12 | P6: =N6-O6
A7: Dairy & eggs | N7: =SUM(B7:M7) | O7: ='Setup & Targets'!C18*12 | P7: =N7-O7
A8: Pantry & grains | N8: =SUM(B8:M8) | O8: ='Setup & Targets'!C19*12 | P8: =N8-O8
A9: Household & misc | N9: =SUM(B9:M9) | O9: ='Setup & Targets'!C20*12 | P9: =N9-O9
A10: TOTAL | B10: =SUM(B5:B9) | C10: =SUM(C5:C9) | D10: =SUM(D5:D9) | E10: =SUM(E5:E9) | F10: =SUM(F5:F9) | G10: =SUM(G5:G9) | H10: =SUM(H5:H9) | I10: =SUM(I5:I9) | ... P10: =SUM(P5:P9)
A12: Tip: a quick way to fill this in — snap a photo of receipts weekly and jot the category totals here.

Sheet Meal Planner & List
A1: Weekly Meal Planner + Shopping List
A3: Day | B3: Breakfast | C3: Lunch | D3: Dinner
A4: Monday
A5: Tuesday
A6: Wednesday
A7: Thursday
A8: Friday
A9: Saturday
A10: Sunday
A13: Shopping list item | B13: Category | C13: Est. price
A35: Estimated list total: | C35: =SUM(C14:C33)
A36: Weekly budget (from Setup): | C36: ='Setup & Targets'!B11
A37: Remaining: | C37: =C36-C35

Sheet Price Comparison
A1: Price-per-Unit Comparison
A2: Compare products of different sizes — the cheapest sticker price isn't always the best deal.
A4: Product | B4: Store/Brand | C4: Price | D4: Size (oz/lb/count) | E4: Price per unit
E5: =IF(AND(C5>0,D5>0),C5/D5,"")
E6: =IF(AND(C6>0,D6>0),C6/D6,"")
E7: =IF(AND(C7>0,D7>0),C7/D7,"")
E8: =IF(AND(C8>0,D8>0),C8/D8,"")
E9: =IF(AND(C9>0,D9>0),C9/D9,"")
E10: =IF(AND(C10>0,D10>0),C10/D10,"")
E11: =IF(AND(C11>0,D11>0),C11/D11,"")
E12: =IF(AND(C12>0,D12>0),C12/D12,"")
E13: =IF(AND(C13>0,D13>0),C13/D13,"")
E14: =IF(AND(C14>0,D14>0),C14/D14,"")
E15: =IF(AND(C15>0,D15>0),C15/D15,"")
E16: =IF(AND(C16>0,D16>0),C16/D16,"")
... E19: =IF(AND(C19>0,D19>0),C19/D19,"")
